{"name":"root","attributes":{"Description":{"type":23,"value":""},"DisplayDescription":{"type":28,"value":"h03d0c474gb68cg43d0g97f4g784be26d9f90"},"DisplayName":{"type":28,"value":"h794117b8g3a50g4399gb755gc446b1d0837b"},"Icon":{"type":23,"value":""},"Name":{"type":23,"value":"WIZARD"},"UUID":{"type":31,"value":"6fe3ae27-dc6c-4fc9-9245-710c790c396c"}},"children":[{"name":"Categories","attributes":{},"children":[{"name":"Category","attributes":{"Name":{"type":23,"value":"Code"}},"children":[]},{"name":"Category","attributes":{"Name":{"type":23,"value":"Dialog"}},"children":[]},{"name":"Category","attributes":{"Name":{"type":23,"value":"Class"}},"children":[]},{"name":"Category","attributes":{"Name":{"type":23,"value":"CharacterSheet"}},"children":[]}]}]}